wireguard_tui/__init__.py
wireguard_tui/wireguard_tui.py
wireguard_tui-0.1.0.dist-info/licenses/LICENSE
wireguard_tui-0.1.0.dist-info/METADATA
wireguard_tui-0.1.0.dist-info/WHEEL
wireguard_tui-0.1.0.dist-info/entry_points.txt
wireguard_tui-0.1.0.dist-info/top_level.txt
wireguard_tui-0.1.0.dist-info/RECORD
