Metadata-Version: 2.4
Name: wireguard-tui
Version: 0.1.0
Summary: A simple TUI for managing WireGuard VPN on Linux.
Author-email: ion <io1n@proton.me>
License: MIT
Project-URL: Homepage, https://github.com/nefr7t/wireguard-tui
Project-URL: Issues, https://github.com/nefr7t/wireguard-tui/issues
Keywords: wireguard,vpn,tui,linux
Requires-Python: >=3.8
License-File: LICENSE
Requires-Dist: colorama
Dynamic: license-file
